[{"newCode":"1210126276","title":"新力上海柳岸春风","purpose":"别墅","x":120.927855,"y":31.14994,"price_num":"待定","price_unit":"","minarea":0,"maxarea":0},{"newCode":"1210126262","title":"中海九峯里","purpose":"住宅","x":121.133495,"y":31.028766,"price_num":"待定","price_unit":"","minarea":0,"maxarea":0},{"newCode":"1210126236","title":"同济华城玫瑰公馆","purpose":"住宅","x":121.397672,"y":31.158918,"price_num":"待定","price_unit":"","minarea":96,"maxarea":144},{"newCode":"1210126190","title":"中粮南桥锦云","purpose":"住宅","x":121.484473,"y":30.920886,"price_num":"待定","price_unit":"","minarea":78,"maxarea":130},{"newCode":"1210126118","title":"枫溪别院","purpose":"别墅","x":121.01395,"y":30.893368,"price_num":"待定","price_unit":"","minarea":155,"maxarea":211},{"newCode":"1210126022","title":"滴水湖馨苑悦湾","purpose":"住宅","x":121.899881,"y":30.893691,"price_num":"待定","price_unit":"","minarea":0,"maxarea":0},{"newCode":"1210126018","title":"公元2040","purpose":"住宅","x":121.768283,"y":31.105601,"price_num":"待定","price_unit":"","minarea":0,"maxarea":0},{"newCode":"1210126016","title":"阳光里","purpose":"住宅","x":121.258433,"y":31.343263,"price_num":"待定","price_unit":"","minarea":0,"maxarea":0},{"newCode":"1210125946","title":"灿辉晶典1733","purpose":"别墅","x":121.284577,"y":31.166428,"price_num":"待定","price_unit":"","minarea":0,"maxarea":0},{"newCode":"1210125944","title":"泰禾大城小院","purpose":"住宅","x":121.696011,"y":31.401506,"price_num":"待定","price_unit":"","minarea":0,"maxarea":0},{"newCode":"1210125936","title":"水悦堂","purpose":"别墅","x":121.039817,"y":31.123265,"price_num":"待定","price_unit":"","minarea":0,"maxarea":0},{"newCode":"1210125934","title":"浦东新区新场旅游综合服务区A10-1地块","purpose":"住宅","x":121.665209,"y":31.033465,"price_num":"待定","price_unit":"","minarea":0,"maxarea":0},{"newCode":"1210125932","title":"同济晶萃","purpose":"住宅","x":121.247155,"y":31.118558,"price_num":"待定","price_unit":"","minarea":0,"maxarea":0},{"newCode":"1210125930","title":"合景天悦","purpose":"住宅","x":121.224241,"y":31.061336,"price_num":"待定","price_unit":"","minarea":0,"maxarea":0},{"newCode":"1210125928","title":"朱家角镇淀惠路北侧35-04地块","purpose":"住宅","x":121.076374,"y":31.135942,"price_num":"待定","price_unit":"","minarea":0,"maxarea":0},{"newCode":"1210125920","title":"盈浦街道胜利路西侧02-01地块","purpose":"住宅","x":121.100435,"y":31.163399,"price_num":"待定","price_unit":"","minarea":0,"maxarea":0},{"newCode":"1210125914","title":"西虹桥壹号","purpose":"住宅","x":121.080574,"y":31.13833,"price_num":"待定","price_unit":"","minarea":82,"maxarea":120},{"newCode":"1210125894","title":"融创壹号府","purpose":"住宅","x":121.260702,"y":31.122968,"price_num":"待定","price_unit":"","minarea":0,"maxarea":0},{"newCode":"1210125890","title":"原筑江南","purpose":"别墅","x":121.581038,"y":30.92096,"price_num":"待定","price_unit":"","minarea":0,"maxarea":0},{"newCode":"1210125872","title":"保利象屿公园悦府","purpose":"住宅","x":121.489781,"y":30.951597,"price_num":"待定","price_unit":"","minarea":0,"maxarea":0},{"newCode":"1210125850","title":"西郊金茂府","purpose":"住宅","x":121.261962,"y":31.326997,"price_num":"待定","price_unit":"","minarea":0,"maxarea":0},{"newCode":"1210125842","title":"奉贤南桥新城15单元23A-01A地块","purpose":"住宅","x":121.508715,"y":30.966107,"price_num":"待定","price_unit":"","minarea":0,"maxarea":0},{"newCode":"1210125840","title":"凤鸣美谷","purpose":"住宅","x":121.460732,"y":30.870902,"price_num":"待定","price_unit":"","minarea":0,"maxarea":0},{"newCode":"1210125822","title":"金融街融府","purpose":"住宅","x":121.451205,"y":31.252881,"price_num":"待定","price_unit":"","minarea":89,"maxarea":168},{"newCode":"1210125808","title":"融创滨江壹号院","purpose":"住宅","x":121.485042,"y":31.198538,"price_num":"待定","price_unit":"","minarea":162,"maxarea":410},{"newCode":"1210125804","title":"安亭新镇","purpose":"别墅","x":121.167732,"y":31.271799,"price_num":"待定","price_unit":"","minarea":116,"maxarea":130},{"newCode":"1210125798","title":"恒大滨江华府","purpose":"住宅","x":121.528273,"y":31.24179,"price_num":"待定","price_unit":"","minarea":0,"maxarea":0},{"newCode":"1210125774","title":"前滩东方逸品","purpose":"住宅","x":121.477749,"y":31.151123,"price_num":"待定","price_unit":"","minarea":0,"maxarea":0},{"newCode":"1210125726","title":"凯利海华府","purpose":"住宅","x":121.52085,"y":31.174441,"price_num":"待定","price_unit":"","minarea":0,"maxarea":0},{"newCode":"1210125696","title":"盛世荟庭","purpose":"住宅","x":121.777519,"y":31.057147,"price_num":"待定","price_unit":"","minarea":84,"maxarea":116},{"newCode":"1211288962","title":"中梁秀湖壹號院","purpose":"住宅","x":120.677121,"y":30.77334,"price_num":"待定","price_unit":"","minarea":89,"maxarea":143},{"newCode":"1210125684","title":"临港蓝湾诚园","purpose":"住宅","x":121.74056,"y":30.881434,"price_num":"待定","price_unit":"","minarea":0,"maxarea":0},{"newCode":"1210125562","title":"禹洲雍贤府","purpose":"住宅","x":121.516475,"y":30.97377,"price_num":"待定","price_unit":"","minarea":83,"maxarea":90},{"newCode":"1210125522","title":"静安府西区","purpose":"住宅","x":121.441756,"y":31.293435,"price_num":"待定","price_unit":"","minarea":95,"maxarea":135},{"newCode":"1210125516","title":"银河丽湾二期","purpose":"住宅","x":121.493504,"y":30.918605,"price_num":"待定","price_unit":"","minarea":0,"maxarea":0},{"newCode":"1210125514","title":"华发公馆","purpose":"住宅","x":121.542742,"y":31.274792,"price_num":"待定","price_unit":"","minarea":128,"maxarea":128},{"newCode":"1210125490","title":"望园豪庭","purpose":"住宅","x":121.487934,"y":30.921917,"price_num":"待定","price_unit":"","minarea":0,"maxarea":0},{"newCode":"1210125456","title":"森兰名轩二期","purpose":"住宅","x":121.590919,"y":31.288833,"price_num":"待定","price_unit":"","minarea":0,"maxarea":0},{"newCode":"1210125436","title":"中粮前滩海景壹号","purpose":"住宅","x":121.480984,"y":31.160653,"price_num":"待定","price_unit":"","minarea":91,"maxarea":130},{"newCode":"1210125426","title":"信达泰禾·上海院子","purpose":"别墅","x":121.507053,"y":31.321098,"price_num":"待定","price_unit":"","minarea":0,"maxarea":0},{"newCode":"1210125378","title":"大华斐勒公园","purpose":"住宅","x":121.5253,"y":31.179498,"price_num":"92000","price_unit":"元/平","minarea":93,"maxarea":105},{"newCode":"1210125358","title":"滨江一品苑","purpose":"住宅","x":121.518029,"y":31.205267,"price_num":"待定","price_unit":"","minarea":131,"maxarea":226},{"newCode":"1210125354","title":"朗诗新西郊","purpose":"住宅","x":121.379699,"y":31.206551,"price_num":"待定","price_unit":"","minarea":180,"maxarea":232},{"newCode":"1210125314","title":"新华联奥莱悦府","purpose":"住宅","x":121.224533,"y":31.166413,"price_num":"待定","price_unit":"","minarea":83,"maxarea":175},{"newCode":"1210125308","title":"秋月朗庭尚东区","purpose":"住宅","x":121.521931,"y":30.924474,"price_num":"待定","price_unit":"","minarea":80,"maxarea":125},{"newCode":"1210125304","title":"UNICITY万科天空之城","purpose":"住宅","x":121.257113,"y":31.174611,"price_num":"待定","price_unit":"","minarea":0,"maxarea":0},{"newCode":"1210125292","title":"金地玺华邨","purpose":"别墅","x":121.254926,"y":31.115576,"price_num":"900","price_unit":"万元/套","minarea":120,"maxarea":158},{"newCode":"1210125264","title":"葛洲坝虹桥紫郡公馆","purpose":"住宅","x":121.316179,"y":31.161712,"price_num":"待定","price_unit":"","minarea":113,"maxarea":182},{"newCode":"1210125182","title":"宫园巧筑","purpose":"别墅","x":121.364068,"y":31.403099,"price_num":"待定","price_unit":"","minarea":135,"maxarea":231},{"newCode":"1210125130","title":"滨江公园壹号","purpose":"住宅","x":121.38082,"y":31.325998,"price_num":"待定","price_unit":"","minarea":0,"maxarea":0},{"newCode":"1210125124","title":"陆家嘴壹号院","purpose":"住宅","x":121.524923,"y":31.242719,"price_num":"待定","price_unit":"","minarea":0,"maxarea":0},{"newCode":"1210125060","title":"海上湾闻涧公寓","purpose":"住宅","x":121.03185,"y":31.115032,"price_num":"待定","price_unit":"","minarea":0,"maxarea":0},{"newCode":"1210125048","title":"新城上坤樾山璟里","purpose":"住宅","x":121.2392,"y":31.096592,"price_num":"待定","price_unit":"","minarea":0,"maxarea":0},{"newCode":"1210124964","title":"龙湖天璞雅筑","purpose":"住宅","x":121.325821,"y":31.270451,"price_num":"待定","price_unit":"","minarea":80,"maxarea":117},{"newCode":"1210124940","title":"古北金鹰府","purpose":"住宅","x":121.381207,"y":31.184132,"price_num":"待定","price_unit":"","minarea":0,"maxarea":0},{"newCode":"1210124924","title":"绿都绣云里","purpose":"住宅","x":121.710731,"y":31.109088,"price_num":"待定","price_unit":"","minarea":0,"maxarea":0},{"newCode":"1210124916","title":"嘉泷汇","purpose":"住宅","x":121.589512,"y":31.254773,"price_num":"待定","price_unit":"","minarea":0,"maxarea":0},{"newCode":"1210124858","title":"海上湾闻涧","purpose":"别墅","x":121.031765,"y":31.115055,"price_num":"待定","price_unit":"","minarea":0,"maxarea":0},{"newCode":"1210124806","title":"保利铃兰公馆","purpose":"住宅","x":121.919176,"y":30.918689,"price_num":"待定","price_unit":"","minarea":0,"maxarea":0},{"newCode":"1210124796","title":"绿地天呈","purpose":"住宅","x":121.240414,"y":31.396929,"price_num":"待定","price_unit":"","minarea":90,"maxarea":152},{"newCode":"1210124582","title":"大华碧云天","purpose":"住宅","x":121.395539,"y":31.29129,"price_num":"待定","price_unit":"","minarea":83,"maxarea":144},{"newCode":"1210124574","title":"阳光城滨江悦","purpose":"住宅","x":121.533728,"y":31.255574,"price_num":"待定","price_unit":"","minarea":135,"maxarea":155},{"newCode":"1210124564","title":"深城投十一街区","purpose":"住宅","x":121.275485,"y":31.328598,"price_num":"待定","price_unit":"","minarea":0,"maxarea":0},{"newCode":"1210124526","title":"上海派II","purpose":"住宅","x":121.197637,"y":31.293017,"price_num":"待定","price_unit":"","minarea":0,"maxarea":0},{"newCode":"1210124506","title":"趣园","purpose":"住宅","x":121.382132,"y":31.192217,"price_num":"待定","price_unit":"","minarea":0,"maxarea":0},{"newCode":"1210124504","title":"禹洲东滩雍禧","purpose":"别墅","x":121.811332,"y":31.497136,"price_num":"35000","price_unit":"元/平","minarea":108,"maxarea":116},{"newCode":"1211284208","title":"花园里","purpose":"住宅","x":121.262163,"y":31.343623,"price_num":"待定","price_unit":"","minarea":0,"maxarea":0},{"newCode":"1211282380","title":"海上郡","purpose":"别墅","x":121.020984,"y":31.118263,"price_num":"待定","price_unit":"","minarea":0,"maxarea":0},{"newCode":"1211282306","title":"万科金域澜湾","purpose":"住宅","x":121.924078,"y":30.915019,"price_num":"待定","price_unit":"","minarea":75,"maxarea":131},{"newCode":"1211281790","title":"水榭兰亭","purpose":"住宅","x":121.664735,"y":30.914415,"price_num":"待定","price_unit":"","minarea":90,"maxarea":123},{"newCode":"1211279590","title":"张江三湘海尚","purpose":"住宅","x":121.622729,"y":31.171051,"price_num":"待定","price_unit":"","minarea":86,"maxarea":135},{"newCode":"1211279088","title":"天和尚上海","purpose":"住宅","x":121.553561,"y":30.977033,"price_num":"待定","price_unit":"","minarea":77,"maxarea":88},{"newCode":"1211276364","title":"金地都会艺境别墅","purpose":"别墅","x":121.344816,"y":31.076142,"price_num":"待定","price_unit":"","minarea":0,"maxarea":0},{"newCode":"1211274718","title":"海珀黄浦","purpose":"住宅","x":121.491635,"y":31.209126,"price_num":"待定","price_unit":"","minarea":0,"maxarea":0},{"newCode":"1211266156","title":"翠湖天地隽荟","purpose":"住宅","x":121.476879,"y":31.217921,"price_num":"待定","price_unit":"","minarea":0,"maxarea":0},{"newCode":"1211263798","title":"港城滴水湖馨苑城萃","purpose":"住宅","x":121.908486,"y":30.893737,"price_num":"待定","price_unit":"","minarea":0,"maxarea":0},{"newCode":"1211253326","title":"东原逸墅","purpose":"别墅","x":121.774537,"y":31.057826,"price_num":"待定","price_unit":"","minarea":0,"maxarea":0},{"newCode":"1211242666","title":"东亚威尼斯公馆二期","purpose":"住宅","x":121.431245,"y":31.628153,"price_num":"待定","price_unit":"","minarea":80,"maxarea":140},{"newCode":"1211242360","title":"虹桥融景","purpose":"住宅","x":121.301646,"y":31.17408,"price_num":"待定","price_unit":"","minarea":350,"maxarea":350},{"newCode":"1211236968","title":"富绅时代公馆","purpose":"住宅","x":121.09586,"y":31.161343,"price_num":"待定","price_unit":"","minarea":0,"maxarea":0},{"newCode":"1211235634","title":"万科安亭新镇","purpose":"住宅","x":121.176952,"y":31.269127,"price_num":"待定","price_unit":"","minarea":0,"maxarea":0},{"newCode":"1211226090","title":"阳明花园","purpose":"住宅","x":121.592213,"y":31.336471,"price_num":"待定","price_unit":"","minarea":0,"maxarea":0},{"newCode":"1211223962","title":"中国铁建青秀城二期","purpose":"住宅","x":121.398299,"y":31.361582,"price_num":"待定","price_unit":"","minarea":120,"maxarea":162},{"newCode":"1211218506","title":"夏都融庭","purpose":"别墅","x":121.293554,"y":31.170831,"price_num":"待定","price_unit":"","minarea":0,"maxarea":0},{"newCode":"1211214920","title":"金地天地云墅","purpose":"住宅","x":121.390069,"y":31.360235,"price_num":"待定","price_unit":"","minarea":100,"maxarea":126},{"newCode":"1211206674","title":"世茂云图","purpose":"住宅","x":121.54516,"y":31.116107,"price_num":"待定","price_unit":"","minarea":87,"maxarea":140},{"newCode":"1211206588","title":"英庭名墅","purpose":"别墅","x":121.320447,"y":31.163095,"price_num":"待定","price_unit":"","minarea":226,"maxarea":515},{"newCode":"1211204950","title":"九龙仓滨江壹十八","purpose":"住宅","x":121.515257,"y":31.213879,"price_num":"待定","price_unit":"","minarea":296,"maxarea":410},{"newCode":"1211201242","title":"泛海国际住区","purpose":"住宅","x":121.49861,"y":31.216625,"price_num":"待定","price_unit":"","minarea":0,"maxarea":0},{"newCode":"1211200774","title":"国浩长风汇都","purpose":"住宅","x":121.388453,"y":31.229373,"price_num":"待定","price_unit":"","minarea":150,"maxarea":225},{"newCode":"1211199798","title":"丽都璟庭","purpose":"住宅","x":121.812914,"y":30.906079,"price_num":"待定","price_unit":"","minarea":0,"maxarea":0},{"newCode":"1211193814","title":"复兴珑御","purpose":"住宅","x":121.484676,"y":31.216439,"price_num":"待定","price_unit":"","minarea":0,"maxarea":0},{"newCode":"1211192140","title":"佳源梦想广场三期","purpose":"住宅","x":121.512903,"y":30.850156,"price_num":"待定","price_unit":"","minarea":90,"maxarea":120},{"newCode":"1211190886","title":"融创外滩188","purpose":"住宅","x":121.495346,"y":31.252362,"price_num":"待定","price_unit":"","minarea":0,"maxarea":0},{"newCode":"1211190600","title":"绿洲康城亲水湾雅颂","purpose":"住宅","x":121.579009,"y":31.148954,"price_num":"待定","price_unit":"","minarea":75,"maxarea":75},{"newCode":"1211189800","title":"绿地朱家角1号","purpose":"别墅","x":121.036074,"y":31.110561,"price_num":"待定","price_unit":"","minarea":150,"maxarea":180},{"newCode":"1211189232","title":"华发四季","purpose":"住宅","x":121.621515,"y":31.172486,"price_num":"待定","price_unit":"","minarea":89,"maxarea":147},{"newCode":"1211187958","title":"泷湾","purpose":"别墅","x":121.20574,"y":31.140746,"price_num":"待定","price_unit":"","minarea":279,"maxarea":353},{"newCode":"1211184792","title":"古北名都城三期","purpose":"住宅","x":121.399777,"y":31.185467,"price_num":"待定","price_unit":"","minarea":0,"maxarea":0},{"newCode":"1211178986","title":"恒大名都","purpose":"住宅","x":121.192855,"y":31.292838,"price_num":"待定","price_unit":"","minarea":0,"maxarea":0},{"newCode":"1211178196","title":"品臻園安麓别业","purpose":"别墅","x":121.049057,"y":31.114942,"price_num":"待定","price_unit":"","minarea":0,"maxarea":0},{"newCode":"1211174588","title":"东亚启航公馆","purpose":"住宅","x":121.751191,"y":31.150699,"price_num":"待定","price_unit":"","minarea":78,"maxarea":88},{"newCode":"1211172790","title":"东亚阳光里","purpose":"住宅","x":121.809148,"y":30.906329,"price_num":"待定","price_unit":"","minarea":0,"maxarea":0},{"newCode":"1211172464","title":"金融家","purpose":"住宅","x":121.671867,"y":31.240762,"price_num":"待定","price_unit":"","minarea":88,"maxarea":143},{"newCode":"1211167548","title":"金地自在城3期","purpose":"住宅","x":121.254919,"y":31.11553,"price_num":"待定","price_unit":"","minarea":0,"maxarea":0},{"newCode":"1211155342","title":"法兰西世家","purpose":"别墅","x":121.295281,"y":31.089814,"price_num":"待定","price_unit":"","minarea":266,"maxarea":266},{"newCode":"1211151588","title":"建邦16区二期","purpose":"住宅","x":121.498525,"y":31.267535,"price_num":"待定","price_unit":"","minarea":0,"maxarea":0},{"newCode":"1211145014","title":"万科翡翠公园","purpose":"住宅","x":121.609122,"y":31.179639,"price_num":"待定","price_unit":"","minarea":0,"maxarea":0},{"newCode":"1211140744","title":"美溪里","purpose":"住宅","x":121.284531,"y":30.806526,"price_num":"待定","price_unit":"","minarea":126,"maxarea":187},{"newCode":"1211140740","title":"华纺和成未来派","purpose":"住宅","x":121.318604,"y":30.83196,"price_num":"待定","price_unit":"","minarea":52,"maxarea":119},{"newCode":"1211139950","title":"君悦湾别墅","purpose":"别墅","x":121.276208,"y":31.162031,"price_num":"待定","price_unit":"","minarea":252,"maxarea":264},{"newCode":"1211139138","title":"安高东方御府","purpose":"住宅","x":121.280902,"y":31.319929,"price_num":"待定","price_unit":"","minarea":0,"maxarea":0},{"newCode":"1211138726","title":"翡丽甲第","purpose":"住宅","x":121.518921,"y":31.258664,"price_num":"待定","price_unit":"","minarea":177,"maxarea":240},{"newCode":"1211137916","title":"大宁金茂府","purpose":"住宅","x":121.457094,"y":31.285337,"price_num":"待定","price_unit":"","minarea":0,"maxarea":0},{"newCode":"1211134768","title":"水都南岸二期海上公馆","purpose":"别墅","x":121.053555,"y":31.085398,"price_num":"待定","price_unit":"","minarea":0,"maxarea":0},{"newCode":"1211134444","title":"万科翡翠雅宾利","purpose":"住宅","x":121.47185,"y":31.255895,"price_num":"待定","price_unit":"","minarea":0,"maxarea":0},{"newCode":"1211129350","title":"宛平88","purpose":"住宅","x":121.445292,"y":31.195468,"price_num":"待定","price_unit":"","minarea":0,"maxarea":0},{"newCode":"1211129290","title":"保利翡丽公馆","purpose":"住宅","x":121.259615,"y":31.114853,"price_num":"待定","price_unit":"","minarea":0,"maxarea":0},{"newCode":"1211128216","title":"惠南颐景园","purpose":"住宅","x":121.760264,"y":31.057929,"price_num":"待定","price_unit":"","minarea":0,"maxarea":0},{"newCode":"1211125060","title":"融信铂湾别墅","purpose":"别墅","x":121.235231,"y":31.136969,"price_num":"待定","price_unit":"","minarea":176,"maxarea":204},{"newCode":"1211120198","title":"仁和都市花园","purpose":"住宅","x":121.576315,"y":31.154094,"price_num":"待定","price_unit":"","minarea":69,"maxarea":155},{"newCode":"1211109154","title":"上海檀香湾","purpose":"别墅","x":121.648676,"y":31.028149,"price_num":"待定","price_unit":"","minarea":193,"maxarea":193},{"newCode":"1211106132","title":"合生广富汇","purpose":"别墅","x":121.195531,"y":31.065507,"price_num":"待定","price_unit":"","minarea":262,"maxarea":269},{"newCode":"1211104560","title":"万立城","purpose":"住宅","x":121.178011,"y":31.283242,"price_num":"待定","price_unit":"","minarea":0,"maxarea":0},{"newCode":"1211103006","title":"招商海德名门别墅","purpose":"别墅","x":121.421711,"y":31.391676,"price_num":"待定","price_unit":"","minarea":174,"maxarea":186},{"newCode":"1211097036","title":"尼德兰官邸","purpose":"住宅","x":121.581381,"y":31.333373,"price_num":"待定","price_unit":"","minarea":207,"maxarea":228},{"newCode":"1211095256","title":"路劲上海院子","purpose":"别墅","x":121.174869,"y":31.35076,"price_num":"待定","price_unit":"","minarea":0,"maxarea":0},{"newCode":"1211094894","title":"艺泰一品花园","purpose":"住宅","x":121.72721,"y":31.047636,"price_num":"待定","price_unit":"","minarea":168,"maxarea":186},{"newCode":"1211089308","title":"同润蓝美俊庭","purpose":"住宅","x":121.747937,"y":30.96296,"price_num":"待定","price_unit":"","minarea":88,"maxarea":157},{"newCode":"1211088198","title":"季景铭郡","purpose":"住宅","x":121.320287,"y":31.284109,"price_num":"待定","price_unit":"","minarea":0,"maxarea":0},{"newCode":"1211087952","title":"佳兆业8号别墅","purpose":"别墅","x":121.419459,"y":30.904978,"price_num":"待定","price_unit":"","minarea":160,"maxarea":185},{"newCode":"1211087878","title":"湖畔天下瑞泷","purpose":"别墅","x":121.305626,"y":31.311054,"price_num":"待定","price_unit":"","minarea":0,"maxarea":0},{"newCode":"1211085262","title":"中铁逸都","purpose":"住宅","x":121.129419,"y":31.153973,"price_num":"待定","price_unit":"","minarea":0,"maxarea":0},{"newCode":"1211081506","title":"露香园","purpose":"住宅","x":121.484414,"y":31.226002,"price_num":"待定","price_unit":"","minarea":0,"maxarea":0},{"newCode":"1211079788","title":"佳兆业8号","purpose":"住宅","x":121.418945,"y":30.903657,"price_num":"待定","price_unit":"","minarea":89,"maxarea":119},{"newCode":"1211077322","title":"天和尚海格调","purpose":"别墅","x":121.553561,"y":30.977046,"price_num":"待定","price_unit":"","minarea":0,"maxarea":0},{"newCode":"1211073482","title":"锦绣逸庭别墅","purpose":"别墅","x":121.260653,"y":31.169214,"price_num":"待定","price_unit":"","minarea":0,"maxarea":0},{"newCode":"1211073122","title":"绿城兰园","purpose":"住宅","x":121.266693,"y":31.076823,"price_num":"待定","price_unit":"","minarea":0,"maxarea":0},{"newCode":"1211069664","title":"万科海上传奇","purpose":"住宅","x":121.567706,"y":31.157757,"price_num":"待定","price_unit":"","minarea":95,"maxarea":125},{"newCode":"1211069594","title":"凯德新视界二期","purpose":"住宅","x":121.809787,"y":30.961018,"price_num":"待定","price_unit":"","minarea":0,"maxarea":0},{"newCode":"1211059124","title":"新江湾城D5地块","purpose":"住宅","x":121.511797,"y":31.325542,"price_num":"待定","price_unit":"","minarea":0,"maxarea":0},{"newCode":"1211056106","title":"蓝湖湾","purpose":"住宅","x":121.43377,"y":31.789323,"price_num":"待定","price_unit":"","minarea":0,"maxarea":0},{"newCode":"1211046594","title":"中福浦江汇","purpose":"住宅","x":121.498152,"y":31.208603,"price_num":"待定","price_unit":"","minarea":46,"maxarea":94},{"newCode":"1211039976","title":"半岛君望","purpose":"别墅","x":121.469078,"y":30.936636,"price_num":"待定","price_unit":"","minarea":0,"maxarea":0},{"newCode":"1211030778","title":"君地蔚林半岛","purpose":"别墅","x":121.458268,"y":31.782601,"price_num":"待定","price_unit":"","minarea":189,"maxarea":226},{"newCode":"1211024472","title":"中冶枫郡","purpose":"住宅","x":121.01931,"y":30.909575,"price_num":"待定","price_unit":"","minarea":0,"maxarea":0},{"newCode":"1210975758","title":"凯迪赫菲庄园","purpose":"别墅","x":121.229424,"y":31.129471,"price_num":"待定","price_unit":"","minarea":0,"maxarea":0},{"newCode":"1210971594","title":"上实海上荟","purpose":"住宅","x":121.278403,"y":31.339783,"price_num":"待定","price_unit":"","minarea":0,"maxarea":0},{"newCode":"1210950104","title":"绿岛江湾城","purpose":"住宅","x":121.448923,"y":31.781552,"price_num":"待定","price_unit":"","minarea":57,"maxarea":225},{"newCode":"1210937398","title":"丝庐雅苑别墅","purpose":"别墅","x":121.656851,"y":31.032444,"price_num":"待定","price_unit":"","minarea":0,"maxarea":0},{"newCode":"1210929932","title":"日月光伯爵天地","purpose":"住宅","x":121.243346,"y":31.39516,"price_num":"待定","price_unit":"","minarea":92,"maxarea":106},{"newCode":"1210921594","title":"海上纳缇","purpose":"住宅","x":121.328007,"y":30.753738,"price_num":"待定","price_unit":"","minarea":0,"maxarea":0},{"newCode":"1210921510","title":"嘉涛湾","purpose":"别墅","x":121.037706,"y":31.109455,"price_num":"待定","price_unit":"","minarea":363,"maxarea":386},{"newCode":"1210918452","title":"华润中央公园别墅","purpose":"别墅","x":121.314758,"y":31.310636,"price_num":"待定","price_unit":"","minarea":0,"maxarea":0},{"newCode":"1210913530","title":"新湖青蓝国际","purpose":"住宅","x":121.473345,"y":31.263704,"price_num":"待定","price_unit":"","minarea":0,"maxarea":0},{"newCode":"1210894414","title":"凯迪迪美逊","purpose":"住宅","x":121.472649,"y":31.193841,"price_num":"待定","price_unit":"","minarea":200,"maxarea":200},{"newCode":"1210893966","title":"湖畔天下","purpose":"住宅","x":121.305472,"y":31.312386,"price_num":"待定","price_unit":"","minarea":103,"maxarea":113},{"newCode":"1210893960","title":"九龙仓静安壹号","purpose":"住宅","x":121.436718,"y":31.225033,"price_num":"待定","price_unit":"","minarea":162,"maxarea":171},{"newCode":"1210878112","title":"水都南岸一期MOMA别墅","purpose":"别墅","x":121.057584,"y":31.087665,"price_num":"待定","price_unit":"","minarea":205,"maxarea":205},{"newCode":"1210874666","title":"新虹桥首府","purpose":"住宅","x":121.304471,"y":31.150539,"price_num":"待定","price_unit":"","minarea":86,"maxarea":118},{"newCode":"1210868786","title":"嘉天汇","purpose":"住宅","x":121.436177,"y":31.223218,"price_num":"待定","price_unit":"","minarea":0,"maxarea":0},{"newCode":"1210859210","title":"金沙御墅","purpose":"别墅","x":121.371881,"y":31.233957,"price_num":"待定","price_unit":"","minarea":0,"maxarea":0},{"newCode":"1210857590","title":"万安世家华园","purpose":"别墅","x":121.157151,"y":30.898243,"price_num":"待定","price_unit":"","minarea":0,"maxarea":0},{"newCode":"1210857340","title":"嘉御庭","purpose":"住宅","x":121.460617,"y":31.206495,"price_num":"待定","price_unit":"","minarea":0,"maxarea":0},{"newCode":"1210856108","title":"嘉业海悦别墅","purpose":"别墅","x":121.53328,"y":30.822292,"price_num":"待定","price_unit":"","minarea":291,"maxarea":291},{"newCode":"1210843504","title":"朱家角新城鸿玺郡","purpose":"别墅","x":121.046153,"y":31.121057,"price_num":"待定","price_unit":"","minarea":0,"maxarea":0},{"newCode":"1210833262","title":"水都南岸一期MOMA洋房","purpose":"住宅","x":121.05727,"y":31.087266,"price_num":"待定","price_unit":"","minarea":93,"maxarea":93},{"newCode":"1210799852","title":"春申景城MID-TOWN","purpose":"住宅","x":121.409041,"y":31.111551,"price_num":"待定","price_unit":"","minarea":0,"maxarea":0},{"newCode":"1210795670","title":"堤亚纳昱墅","purpose":"别墅","x":121.429473,"y":31.677755,"price_num":"待定","price_unit":"","minarea":290,"maxarea":310},{"newCode":"1210771624","title":"华润外滩九里","purpose":"住宅","x":121.503462,"y":31.219009,"price_num":"待定","price_unit":"","minarea":0,"maxarea":0},{"newCode":"1210718342","title":"东外滩1号","purpose":"住宅","x":121.555264,"y":31.273877,"price_num":"待定","price_unit":"","minarea":94,"maxarea":161},{"newCode":"1210691818","title":"浦东星河湾","purpose":"住宅","x":121.53459,"y":31.192631,"price_num":"待定","price_unit":"","minarea":245,"maxarea":375},{"newCode":"1210687178","title":"八埭头滨江园","purpose":"住宅","x":121.522916,"y":31.252705,"price_num":"待定","price_unit":"","minarea":110,"maxarea":240},{"newCode":"1210642602","title":"紫竹半岛","purpose":"住宅","x":121.467822,"y":31.027351,"price_num":"待定","price_unit":"","minarea":73,"maxarea":104},{"newCode":"1210543622","title":"长泰西郊别墅","purpose":"别墅","x":121.286219,"y":31.090659,"price_num":"待定","price_unit":"","minarea":0,"maxarea":0},{"newCode":"1210505422","title":"朱家角新城隽苑","purpose":"住宅","x":121.046083,"y":31.119349,"price_num":"待定","price_unit":"","minarea":90,"maxarea":140},{"newCode":"1210200222","title":"贝尚湾","purpose":"住宅","x":121.319947,"y":31.146187,"price_num":"待定","price_unit":"","minarea":104,"maxarea":175},{"newCode":"1210140782","title":"百汇园","purpose":"住宅","x":121.460551,"y":31.171347,"price_num":"待定","price_unit":"","minarea":110,"maxarea":125},{"newCode":"1210076241","title":"静安豪景苑","purpose":"住宅","x":121.447448,"y":31.232612,"price_num":"待定","price_unit":"","minarea":0,"maxarea":0},{"newCode":"1210069724","title":"海源别墅","purpose":"别墅","x":121.031437,"y":31.117995,"price_num":"待定","price_unit":"","minarea":0,"maxarea":0},{"newCode":"1210062704","title":"南京西路公馆","purpose":"住宅","x":121.437629,"y":31.219975,"price_num":"待定","price_unit":"","minarea":0,"maxarea":0},{"newCode":"1210027276","title":"上海紫园二期","purpose":"别墅","x":121.192286,"y":31.08679,"price_num":"待定","price_unit":"","minarea":0,"maxarea":0},{"newCode":"1210125020","title":"东外滩17公馆","purpose":"写字楼","x":121.556577,"y":31.27231,"price_num":"65000","price_unit":"元/平","minarea":0,"maxarea":0},{"newCode":"1211274726","title":"悦立方商业广场","purpose":"写字楼","x":121.346547,"y":30.750407,"price_num":"38000","price_unit":"元/平","minarea":0,"maxarea":0},{"newCode":"1211257652","title":"绿地海岸城","purpose":"写字楼","x":121.727932,"y":31.228015,"price_num":"25000","price_unit":"元/平","minarea":0,"maxarea":0},{"newCode":"1211201992","title":"阳光城MODO","purpose":"写字楼","x":121.65609,"y":31.21452,"price_num":"800","price_unit":"万元/套","minarea":0,"maxarea":0},{"newCode":"1210126156","title":"荣湾府","purpose":"住宅","x":121.843889,"y":29.168543,"price_num":"9000","price_unit":"元/平","minarea":0,"maxarea":0},{"newCode":"1210125978","title":"尚景丽园","purpose":"住宅","x":121.573061,"y":31.12059,"price_num":"40000","price_unit":"元/平","minarea":0,"maxarea":0},{"newCode":"1211289380","title":"开元万科新都会","purpose":"住宅","x":120.670372,"y":30.493829,"price_num":"14500","price_unit":"元/平","minarea":94,"maxarea":134},{"newCode":"1211289342","title":"华夏东城一品","purpose":"住宅","x":120.47779,"y":31.608492,"price_num":"11500","price_unit":"元/平","minarea":82,"maxarea":136},{"newCode":"1211289332","title":"金海丽水湾","purpose":"住宅","x":120.446166,"y":32.551217,"price_num":"7500","price_unit":"元/平","minarea":0,"maxarea":0},{"newCode":"1211289328","title":"华悦尚品","purpose":"住宅","x":120.464701,"y":31.836034,"price_num":"8000","price_unit":"元/平","minarea":123,"maxarea":170},{"newCode":"1211289324","title":"卡森卫星城","purpose":"住宅","x":120.632436,"y":30.494735,"price_num":"9000","price_unit":"元/平","minarea":88,"maxarea":110},{"newCode":"1211289322","title":"苏建优景美地","purpose":"住宅","x":120.472583,"y":32.515063,"price_num":"8300","price_unit":"元/平","minarea":94,"maxarea":199},{"newCode":"1211289318","title":"仁和景苑","purpose":"住宅","x":120.936721,"y":32.051126,"price_num":"8000","price_unit":"元/平","minarea":89,"maxarea":143},{"newCode":"1211289316","title":"南通银河湾","purpose":"住宅","x":121.060579,"y":32.073519,"price_num":"7300","price_unit":"元/平","minarea":0,"maxarea":0},{"newCode":"1210125902","title":"欣悦华庭","purpose":"住宅","x":121.729406,"y":30.941098,"price_num":"20000","price_unit":"元/平","minarea":90,"maxarea":123},{"newCode":"1211289158","title":"中梁壹号院","purpose":"住宅","x":121.508139,"y":29.868677,"price_num":"待定","price_unit":"","minarea":0,"maxarea":0},{"newCode":"1211289156","title":"天瑞绿洲","purpose":"住宅","x":120.552968,"y":32.396179,"price_num":"5000","price_unit":"元/平","minarea":0,"maxarea":0},{"newCode":"1211289152","title":"金科世界城","purpose":"住宅","x":120.548438,"y":32.376529,"price_num":"5700","price_unit":"元/平","minarea":0,"maxarea":0},{"newCode":"1211289150","title":"7星首府","purpose":"住宅","x":120.494131,"y":32.534042,"price_num":"5300","price_unit":"元/平","minarea":0,"maxarea":0},{"newCode":"1211289148","title":"时代尚城","purpose":"住宅","x":121.009455,"y":31.919314,"price_num":"6500","price_unit":"元/平","minarea":0,"maxarea":0},{"newCode":"1211289146","title":"爱法山水国际","purpose":"住宅","x":120.45359,"y":32.514888,"price_num":"4900","price_unit":"元/平","minarea":0,"maxarea":0},{"newCode":"1210125832","title":"禹洲府","purpose":"住宅","x":121.377976,"y":31.021838,"price_num":"46000","price_unit":"元/平","minarea":77,"maxarea":89},{"newCode":"1210125826","title":"盛誉世家","purpose":"住宅","x":121.102501,"y":31.163701,"price_num":"43000","price_unit":"元/平","minarea":105,"maxarea":139},{"newCode":"1210125786","title":"世合理想大地至真里","purpose":"住宅","x":120.849916,"y":30.705859,"price_num":"10500","price_unit":"元/平","minarea":85,"maxarea":135},{"newCode":"1210125772","title":"路劲上海villa","purpose":"别墅","x":121.17523,"y":31.351465,"price_num":"38000","price_unit":"元/平","minarea":131,"maxarea":145},{"newCode":"1210125760","title":"路劲佘山院子","purpose":"住宅","x":121.139171,"y":31.025104,"price_num":"39000","price_unit":"元/平","minarea":70,"maxarea":142},{"newCode":"1210125716","title":"碧桂园玫瑰公馆","purpose":"住宅","x":121.08099,"y":30.872585,"price_num":"200","price_unit":"万元/套","minarea":163,"maxarea":169},{"newCode":"1210125706","title":"东原公馆","purpose":"住宅","x":121.113691,"y":31.147691,"price_num":"30000","price_unit":"元/平","minarea":124,"maxarea":124},{"newCode":"1210125662","title":"新城尚品","purpose":"住宅","x":121.312172,"y":31.063325,"price_num":"33000","price_unit":"元/平","minarea":112,"maxarea":165},{"newCode":"1210125650","title":"长城逸府","purpose":"住宅","x":121.031056,"y":30.898689,"price_num":"250","price_unit":"万元/套","minarea":120,"maxarea":266},{"newCode":"1210125586","title":"碧桂园湖悦天境花园","purpose":"住宅","x":120.856548,"y":31.032066,"price_num":"18500","price_unit":"元/平","minarea":95,"maxarea":150},{"newCode":"1210125502","title":"阜兴世纪公馆","purpose":"住宅","x":121.528615,"y":31.224871,"price_num":"80000","price_unit":"元/平","minarea":100,"maxarea":156},{"newCode":"1210125448","title":"银亿公园壹号","purpose":"住宅","x":121.551549,"y":31.2106,"price_num":"125000","price_unit":"元/平","minarea":170,"maxarea":182},{"newCode":"1210125434","title":"朱家角新城观澜府","purpose":"别墅","x":121.051115,"y":31.123167,"price_num":"36000","price_unit":"元/平","minarea":160,"maxarea":160},{"newCode":"1210125422","title":"融创浦建路727","purpose":"住宅","x":121.530703,"y":31.208219,"price_num":"75000","price_unit":"元/平","minarea":94,"maxarea":134},{"newCode":"1210125388","title":"宝龙世家","purpose":"住宅","x":121.849913,"y":30.868545,"price_num":"23000","price_unit":"元/平","minarea":115,"maxarea":115},{"newCode":"1210125376","title":"中骏天悦","purpose":"住宅","x":121.401145,"y":31.255469,"price_num":"105000","price_unit":"元/平","minarea":118,"maxarea":128},{"newCode":"1210125372","title":"路劲上海院子雅院","purpose":"别墅","x":121.177016,"y":31.347716,"price_num":"380","price_unit":"万元/套","minarea":121,"maxarea":143},{"newCode":"1210125296","title":"浦江坤庭二期","purpose":"住宅","x":121.491974,"y":31.078985,"price_num":"60000","price_unit":"元/平","minarea":97,"maxarea":156},{"newCode":"1210125290","title":"禹洲丁香里","purpose":"住宅","x":121.273538,"y":31.409266,"price_num":"32000","price_unit":"元/平","minarea":116,"maxarea":138},{"newCode":"1210125280","title":"金地都会艺境","purpose":"住宅","x":121.344816,"y":31.07614,"price_num":"41000","price_unit":"元/平","minarea":90,"maxarea":90},{"newCode":"1210125278","title":"安亭瑞仕锦庭","purpose":"住宅","x":121.189486,"y":31.275475,"price_num":"31500","price_unit":"元/平","minarea":99,"maxarea":164},{"newCode":"1210125258","title":"上海西环中心星信名邸","purpose":"住宅","x":121.30374,"y":31.304628,"price_num":"49000","price_unit":"元/平","minarea":85,"maxarea":113},{"newCode":"1210125242","title":"晶耀名邸","purpose":"住宅","x":121.476131,"y":31.150991,"price_num":"待定","price_unit":"","minarea":0,"maxarea":0},{"newCode":"1210125234","title":"中南君悦府","purpose":"住宅","x":121.078008,"y":31.135735,"price_num":"42000","price_unit":"元/平","minarea":114,"maxarea":132},{"newCode":"1210125210","title":"融信铂爵","purpose":"住宅","x":121.080099,"y":31.135834,"price_num":"42000","price_unit":"元/平","minarea":90,"maxarea":123},{"newCode":"1210125188","title":"澜庭","purpose":"住宅","x":121.314183,"y":30.831892,"price_num":"20000","price_unit":"元/平","minarea":77,"maxarea":78},{"newCode":"1210125136","title":"上海恒大御澜庭","purpose":"别墅","x":121.031976,"y":31.124438,"price_num":"33000","price_unit":"元/平","minarea":78,"maxarea":244},{"newCode":"1210125122","title":"中骏雍景湾","purpose":"别墅","x":121.04307,"y":31.116216,"price_num":"待定","price_unit":"","minarea":100,"maxarea":117},{"newCode":"1210125112","title":"远洋丽兹堡","purpose":"别墅","x":121.365891,"y":31.401346,"price_num":"4800","price_unit":"万元/套","minarea":634,"maxarea":1239},{"newCode":"1210125110","title":"嘉宝前滩后院","purpose":"别墅","x":121.512926,"y":31.15508,"price_num":"90000","price_unit":"元/平","minarea":180,"maxarea":195},{"newCode":"1210125024","title":"景瑞城中公园","purpose":"住宅","x":121.11268,"y":31.157041,"price_num":"42000","price_unit":"元/平","minarea":93,"maxarea":118},{"newCode":"1210125018","title":"东渡悦来城","purpose":"住宅","x":121.084209,"y":31.13621,"price_num":"41000","price_unit":"元/平","minarea":87,"maxarea":126},{"newCode":"1210125002","title":"保利建工西郊锦庐","purpose":"别墅","x":121.230103,"y":31.123731,"price_num":"52000","price_unit":"元/平","minarea":114,"maxarea":125},{"newCode":"1210124996","title":"上实海上公元","purpose":"住宅","x":121.268627,"y":31.34448,"price_num":"42000","price_unit":"元/平","minarea":116,"maxarea":126},{"newCode":"1210124994","title":"东方华璟园","purpose":"住宅","x":121.582111,"y":30.92713,"price_num":"24000","price_unit":"元/平","minarea":104,"maxarea":131},{"newCode":"1210124962","title":"吉宝佘山御庭","purpose":"别墅","x":121.195204,"y":31.097634,"price_num":"60000","price_unit":"元/平","minarea":295,"maxarea":398},{"newCode":"1210124936","title":"阳光星期8","purpose":"住宅","x":121.480414,"y":30.918863,"price_num":"36900","price_unit":"元/平","minarea":83,"maxarea":130},{"newCode":"1210124934","title":"新城上坤樾山美墅","purpose":"别墅","x":121.238004,"y":31.101712,"price_num":"1100","price_unit":"万元/套","minarea":168,"maxarea":168},{"newCode":"1210124892","title":"臻水岸苑","purpose":"别墅","x":121.22488,"y":31.141939,"price_num":"1300","price_unit":"万元/套","minarea":287,"maxarea":294},{"newCode":"1210124770","title":"尚海湾豪庭二期","purpose":"住宅","x":121.461626,"y":31.181546,"price_num":"155000","price_unit":"元/平","minarea":282,"maxarea":286},{"newCode":"1210124764","title":"金隅大成郡","purpose":"住宅","x":121.265546,"y":31.405253,"price_num":"32000","price_unit":"元/平","minarea":121,"maxarea":143},{"newCode":"1210124742","title":"宝业爱多邦","purpose":"住宅","x":121.154723,"y":31.144924,"price_num":"42000","price_unit":"元/平","minarea":75,"maxarea":135},{"newCode":"1210124712","title":"大名城紫金九号","purpose":"住宅","x":121.666678,"y":31.228747,"price_num":"68000","price_unit":"元/平","minarea":91,"maxarea":141},{"newCode":"1210124702","title":"明天华城三期","purpose":"住宅","x":121.577841,"y":31.103643,"price_num":"52200","price_unit":"元/平","minarea":130,"maxarea":149},{"newCode":"1210124696","title":"外冈壹号","purpose":"住宅","x":121.176351,"y":31.357095,"price_num":"25000","price_unit":"元/平","minarea":137,"maxarea":312},{"newCode":"1210124676","title":"静安慕舍","purpose":"住宅","x":121.456623,"y":31.291252,"price_num":"75000","price_unit":"元/平","minarea":147,"maxarea":260},{"newCode":"1210124572","title":"源昌幸福里","purpose":"住宅","x":121.156204,"y":31.158794,"price_num":"42000","price_unit":"元/平","minarea":81,"maxarea":138},{"newCode":"1210124556","title":"佳兆业城市广场郦璟湾","purpose":"住宅","x":121.274724,"y":31.407013,"price_num":"30000","price_unit":"元/平","minarea":137,"maxarea":147},{"newCode":"1211283418","title":"碧桂园嘉誉","purpose":"住宅","x":121.276392,"y":31.418255,"price_num":"38000","price_unit":"元/平","minarea":115,"maxarea":115},{"newCode":"1211283416","title":"圣和静安公馆","purpose":"住宅","x":121.478295,"y":31.246161,"price_num":"110000","price_unit":"元/平","minarea":88,"maxarea":141},{"newCode":"1211280902","title":"华润佘山九里","purpose":"别墅","x":121.261156,"y":31.10555,"price_num":"640","price_unit":"万元/套","minarea":138,"maxarea":167},{"newCode":"1211279916","title":"静安府东区","purpose":"住宅","x":121.442556,"y":31.292191,"price_num":"1700","price_unit":"万元/套","minarea":95,"maxarea":216},{"newCode":"1211267712","title":"中国海南海花岛","purpose":"住宅","x":109.1616,"y":19.656465,"price_num":"14000","price_unit":"元/平","minarea":102,"maxarea":404},{"newCode":"1211262302","title":"绿洲华亭茗苑","purpose":"别墅","x":121.244057,"y":31.465837,"price_num":"25000","price_unit":"元/平","minarea":76,"maxarea":204},{"newCode":"1211255820","title":"优山美地","purpose":"住宅","x":121.23768,"y":30.83285,"price_num":"16000","price_unit":"元/平","minarea":110,"maxarea":135},{"newCode":"1211253698","title":"嘉宝梦之缘景庭","purpose":"住宅","x":121.244351,"y":31.33605,"price_num":"45000","price_unit":"元/平","minarea":76,"maxarea":139},{"newCode":"1211252204","title":"浦发罗兰翡丽","purpose":"住宅","x":121.673546,"y":31.226252,"price_num":"66000","price_unit":"元/平","minarea":117,"maxarea":133},{"newCode":"1211248312","title":"淡水湾花园二期","purpose":"住宅","x":121.475586,"y":31.211643,"price_num":"118000","price_unit":"元/平","minarea":355,"maxarea":355},{"newCode":"1211239524","title":"凯德都会晶彩","purpose":"住宅","x":121.15515,"y":31.287298,"price_num":"24000","price_unit":"元/平","minarea":0,"maxarea":0},{"newCode":"1211236016","title":"绿地海珀佘山","purpose":"住宅","x":121.174242,"y":31.091346,"price_num":"1700","price_unit":"万元/套","minarea":320,"maxarea":360},{"newCode":"1211235948","title":"中粮天悦壹号","purpose":"住宅","x":121.474777,"y":31.242986,"price_num":"130000","price_unit":"元/平","minarea":180,"maxarea":285},{"newCode":"1211226040","title":"大华伊斐墅","purpose":"别墅","x":121.525525,"y":31.17268,"price_num":"110000","price_unit":"元/平","minarea":276,"maxarea":276},{"newCode":"1211218462","title":"荣信虹桥世嘉","purpose":"住宅","x":121.395102,"y":31.174412,"price_num":"70000","price_unit":"元/平","minarea":350,"maxarea":350},{"newCode":"1211213068","title":"金臣汇","purpose":"住宅","x":121.272535,"y":31.204105,"price_num":"65000","price_unit":"元/平","minarea":253,"maxarea":253},{"newCode":"1211210372","title":"恒大御景湾","purpose":"住宅","x":121.279954,"y":31.318679,"price_num":"48000","price_unit":"元/平","minarea":145,"maxarea":210},{"newCode":"1211208126","title":"大发融悦","purpose":"住宅","x":121.085115,"y":31.135514,"price_num":"40000","price_unit":"元/平","minarea":115,"maxarea":139},{"newCode":"1211206004","title":"仁恒公园世纪","purpose":"住宅","x":121.534767,"y":31.207967,"price_num":"125000","price_unit":"元/平","minarea":93,"maxarea":245},{"newCode":"1211201508","title":"同济东时区","purpose":"别墅","x":121.747914,"y":31.146747,"price_num":"46000","price_unit":"元/平","minarea":178,"maxarea":182},{"newCode":"1211200618","title":"葛洲坝绿城玉兰花园","purpose":"住宅","x":121.090759,"y":31.170761,"price_num":"36971","price_unit":"元/平","minarea":102,"maxarea":220},{"newCode":"1211200528","title":"鹏欣一品漫城五期前滩尚城","purpose":"住宅","x":121.491466,"y":31.114085,"price_num":"66000","price_unit":"元/平","minarea":98,"maxarea":115},{"newCode":"1211200344","title":"苏河融景","purpose":"住宅","x":121.456117,"y":31.241445,"price_num":"待定","price_unit":"","minarea":0,"maxarea":0},{"newCode":"1211198638","title":"地产尚海郦景","purpose":"住宅","x":121.538659,"y":31.23908,"price_num":"4000","price_unit":"万元/套","minarea":282,"maxarea":312},{"newCode":"1211196342","title":"东郊罗兰别墅","purpose":"别墅","x":121.609497,"y":31.22583,"price_num":"130000","price_unit":"元/平","minarea":300,"maxarea":413},{"newCode":"1211189704","title":"湖山香颂湾","purpose":"住宅","x":121.337318,"y":30.748368,"price_num":"27000","price_unit":"元/平","minarea":87,"maxarea":127},{"newCode":"1211189658","title":"淮海名邸","purpose":"住宅","x":121.42457,"y":31.200703,"price_num":"130000","price_unit":"元/平","minarea":169,"maxarea":265},{"newCode":"1211189242","title":"安澜西郊","purpose":"别墅","x":121.292269,"y":31.155633,"price_num":"4400","price_unit":"万元/套","minarea":438,"maxarea":1022},{"newCode":"1211188796","title":"恒大佘山首府（备案名：佘北家园荟萃园）","purpose":"住宅","x":121.219262,"y":31.128156,"price_num":"40000","price_unit":"元/平","minarea":218,"maxarea":224},{"newCode":"1211183074","title":"绿地海珀风华","purpose":"别墅","x":121.234689,"y":31.133817,"price_num":"1100","price_unit":"万元/套","minarea":217,"maxarea":217},{"newCode":"1211182860","title":"颐湾丽庭","purpose":"别墅","x":121.035623,"y":31.115639,"price_num":"750","price_unit":"万元/套","minarea":207,"maxarea":306},{"newCode":"1211180408","title":"中铁北城时代","purpose":"住宅","x":121.454038,"y":31.391814,"price_num":"38000","price_unit":"元/平","minarea":90,"maxarea":100},{"newCode":"1211180162","title":"御岛财富公馆","purpose":"住宅","x":121.697714,"y":31.390648,"price_num":"35000","price_unit":"元/平","minarea":115,"maxarea":286},{"newCode":"1211178786","title":"首创禧悦翠庭","purpose":"住宅","x":121.0847,"y":31.131693,"price_num":"41000","price_unit":"元/平","minarea":110,"maxarea":127},{"newCode":"1211178122","title":"中建锦绣天地","purpose":"住宅","x":121.285232,"y":31.183308,"price_num":"60000","price_unit":"元/平","minarea":0,"maxarea":0},{"newCode":"1211174618","title":"万源城御璄","purpose":"住宅","x":121.39317,"y":31.148819,"price_num":"3600","price_unit":"万元/套","minarea":297,"maxarea":408},{"newCode":"1211174604","title":"璟储新和湾","purpose":"别墅","x":121.331428,"y":31.449989,"price_num":"17000","price_unit":"元/平","minarea":0,"maxarea":0},{"newCode":"1211167766","title":"鸿泰乐颐小镇","purpose":"住宅","x":121.420719,"y":31.784309,"price_num":"14000","price_unit":"元/平","minarea":65,"maxarea":65},{"newCode":"1211166142","title":"远洋鸿郡","purpose":"别墅","x":121.366415,"y":31.399264,"price_num":"1900","price_unit":"万元/套","minarea":350,"maxarea":350},{"newCode":"1211165408","title":"仁恒东郊花园","purpose":"住宅","x":121.670557,"y":31.225628,"price_num":"68000","price_unit":"元/平","minarea":134,"maxarea":220},{"newCode":"1211157676","title":"经纬城市绿洲五期学士逸居家园","purpose":"住宅","x":121.40559,"y":31.325971,"price_num":"50000","price_unit":"元/平","minarea":133,"maxarea":133},{"newCode":"1211155618","title":"泰禾红桥","purpose":"住宅","x":121.151877,"y":31.1456,"price_num":"42000","price_unit":"元/平","minarea":89,"maxarea":91},{"newCode":"1211155396","title":"大学里","purpose":"住宅","x":121.210706,"y":31.281345,"price_num":"30000","price_unit":"元/平","minarea":115,"maxarea":115},{"newCode":"1211155216","title":"佘山一品","purpose":"别墅","x":121.175049,"y":31.099365,"price_num":"35000","price_unit":"元/平","minarea":210,"maxarea":360},{"newCode":"1211154068","title":"首创旭辉城","purpose":"住宅","x":121.200331,"y":31.413543,"price_num":"27000","price_unit":"元/平","minarea":88,"maxarea":116},{"newCode":"1211153422","title":"正荣御首府","purpose":"住宅","x":121.318363,"y":30.744365,"price_num":"22000","price_unit":"元/平","minarea":88,"maxarea":128},{"newCode":"1211152918","title":"绿地香缇","purpose":"住宅","x":121.255896,"y":31.119915,"price_num":"50000","price_unit":"元/平","minarea":0,"maxarea":0},{"newCode":"1211144782","title":"西上海御庭","purpose":"住宅","x":121.203686,"y":31.287387,"price_num":"300","price_unit":"万元/套","minarea":90,"maxarea":92},{"newCode":"1211140814","title":"象屿上海年华","purpose":"住宅","x":121.339858,"y":31.074121,"price_num":"45000","price_unit":"元/平","minarea":83,"maxarea":106},{"newCode":"1211140754","title":"蓝湖湾别墅","purpose":"别墅","x":121.430852,"y":31.786239,"price_num":"18500","price_unit":"元/平","minarea":209,"maxarea":260},{"newCode":"1211140730","title":"正荣璟园","purpose":"住宅","x":121.016973,"y":30.897907,"price_num":"19000","price_unit":"元/平","minarea":90,"maxarea":170},{"newCode":"1211136948","title":"仁恒西郊花园","purpose":"住宅","x":121.258239,"y":31.181703,"price_num":"60000","price_unit":"元/平","minarea":94,"maxarea":223},{"newCode":"1211134030","title":"古北壹号","purpose":"住宅","x":121.395999,"y":31.186621,"price_num":"150000","price_unit":"元/平","minarea":385,"maxarea":485},{"newCode":"1211130820","title":"好世凤翔苑","purpose":"住宅","x":121.323292,"y":31.285506,"price_num":"50000","price_unit":"元/平","minarea":84,"maxarea":152},{"newCode":"1211129536","title":"保利天琴宇","purpose":"住宅","x":121.266274,"y":31.35934,"price_num":"40000","price_unit":"元/平","minarea":205,"maxarea":300},{"newCode":"1211126012","title":"祥和王宫","purpose":"别墅","x":121.386258,"y":31.282347,"price_num":"100000","price_unit":"元/平","minarea":570,"maxarea":590},{"newCode":"1211121552","title":"正荣国领","purpose":"别墅","x":121.363673,"y":31.406793,"price_num":"40000","price_unit":"元/平","minarea":145,"maxarea":178},{"newCode":"1211116658","title":"万科翡翠滨江","purpose":"住宅","x":121.540304,"y":31.247147,"price_num":"150000","price_unit":"元/平","minarea":240,"maxarea":380},{"newCode":"1211116510","title":"同润蓝美俊庭别墅","purpose":"别墅","x":121.748992,"y":30.962921,"price_num":"35000","price_unit":"元/平","minarea":150,"maxarea":160},{"newCode":"1211113126","title":"华侨城十号院","purpose":"别墅","x":121.495262,"y":31.100503,"price_num":"100000","price_unit":"元/平","minarea":480,"maxarea":480},{"newCode":"1211112698","title":"步阳御江金都二期","purpose":"住宅","x":121.247158,"y":31.399696,"price_num":"37000","price_unit":"元/平","minarea":177,"maxarea":195},{"newCode":"1211111918","title":"申亚乐庭","purpose":"住宅","x":121.401046,"y":30.903344,"price_num":"325","price_unit":"万元/套","minarea":0,"maxarea":0},{"newCode":"1211111176","title":"毕加索花园小镇","purpose":"住宅","x":121.298341,"y":30.799078,"price_num":"21000","price_unit":"元/平","minarea":78,"maxarea":146},{"newCode":"1211107312","title":"中海紫御世家","purpose":"别墅","x":121.382601,"y":31.228084,"price_num":"140000","price_unit":"元/平","minarea":359,"maxarea":365},{"newCode":"1211106410","title":"金臣别墅","purpose":"别墅","x":121.272114,"y":31.20485,"price_num":"5000","price_unit":"万元/套","minarea":435,"maxarea":435},{"newCode":"1211103478","title":"一品漫城四期壹品别墅","purpose":"别墅","x":121.489343,"y":31.116329,"price_num":"2700","price_unit":"万元/套","minarea":330,"maxarea":330},{"newCode":"1211093636","title":"中洲君廷","purpose":"住宅","x":121.453731,"y":31.180052,"price_num":"120000","price_unit":"元/平","minarea":288,"maxarea":288},{"newCode":"1211092922","title":"东滩花园","purpose":"别墅","x":121.832107,"y":31.453997,"price_num":"40000","price_unit":"元/平","minarea":122,"maxarea":220},{"newCode":"1211089198","title":"绿城乌镇雅园","purpose":"住宅","x":120.512982,"y":30.72345,"price_num":"23000","price_unit":"元/平","minarea":77,"maxarea":128},{"newCode":"1211088132","title":"西郊庄园马德里洋房","purpose":"住宅","x":121.285498,"y":31.20211,"price_num":"70000","price_unit":"元/平","minarea":220,"maxarea":260},{"newCode":"1211087402","title":"世茂佘山里","purpose":"别墅","x":121.175334,"y":31.096204,"price_num":"1350","price_unit":"万元/套","minarea":247,"maxarea":283},{"newCode":"1211083818","title":"盛世御珑湾","purpose":"住宅","x":121.516505,"y":31.317873,"price_num":"80000","price_unit":"元/平","minarea":83,"maxarea":133},{"newCode":"1211078158","title":"高尔夫社区汤泉美地城","purpose":"住宅","x":121.199209,"y":30.87472,"price_num":"19800","price_unit":"元/平","minarea":123,"maxarea":158},{"newCode":"1211078144","title":"虹桥宝龙城","purpose":"商铺","x":121.232474,"y":31.230481,"price_num":"20000","price_unit":"元/平","minarea":0,"maxarea":0},{"newCode":"1211077510","title":"金大元御珑宫廷","purpose":"住宅","x":121.650681,"y":31.202358,"price_num":"2300","price_unit":"万元/套","minarea":360,"maxarea":438},{"newCode":"1211071346","title":"申亚花涧墅","purpose":"别墅","x":121.554453,"y":30.982716,"price_num":"869","price_unit":"万元/套","minarea":248,"maxarea":248},{"newCode":"1211061838","title":"御龙锦园","purpose":"住宅","x":121.354476,"y":30.759736,"price_num":"22000","price_unit":"元/平","minarea":78,"maxarea":101},{"newCode":"1211058272","title":"恒文星尚湾","purpose":"住宅","x":121.23016,"y":31.223176,"price_num":"42000","price_unit":"元/平","minarea":89,"maxarea":129},{"newCode":"1211058246","title":"新江湾城首府别墅","purpose":"别墅","x":121.516965,"y":31.333243,"price_num":"4000","price_unit":"万元/套","minarea":395,"maxarea":395},{"newCode":"1211055662","title":"恒大海上威尼斯","purpose":"住宅","x":121.91613,"y":31.717891,"price_num":"7500","price_unit":"元/平","minarea":136,"maxarea":170},{"newCode":"1211055526","title":"复地御西郊","purpose":"住宅","x":121.358959,"y":31.19942,"price_num":"100000","price_unit":"元/平","minarea":250,"maxarea":480},{"newCode":"1211054850","title":"锦秋御尚","purpose":"住宅","x":121.38366,"y":31.325818,"price_num":"63000","price_unit":"元/平","minarea":206,"maxarea":206},{"newCode":"1211045764","title":"保利天鹅语别墅","purpose":"别墅","x":121.237698,"y":31.350513,"price_num":"1200","price_unit":"万元/套","minarea":255,"maxarea":255},{"newCode":"1211041900","title":"鹏欣一品漫城三期浅山别墅","purpose":"别墅","x":121.491132,"y":31.116234,"price_num":"2500","price_unit":"万元/套","minarea":313,"maxarea":313},{"newCode":"1211039828","title":"华侨城苏河湾塔尖住宅","purpose":"住宅","x":121.481133,"y":31.242202,"price_num":"190000","price_unit":"元/平","minarea":280,"maxarea":518},{"newCode":"1211027490","title":"合生财富海景公馆","purpose":"住宅","x":121.353088,"y":30.727703,"price_num":"27000","price_unit":"元/平","minarea":83,"maxarea":177},{"newCode":"1211018414","title":"西上海君廷","purpose":"别墅","x":121.205797,"y":31.286576,"price_num":"780","price_unit":"万元/套","minarea":224,"maxarea":224},{"newCode":"1210990254","title":"上海高尔夫新城","purpose":"别墅","x":121.197246,"y":30.871759,"price_num":"468","price_unit":"万元/套","minarea":162,"maxarea":319},{"newCode":"1210976102","title":"大华清水湾花园三期华府樟园","purpose":"住宅","x":121.414163,"y":31.2248,"price_num":"95000","price_unit":"元/平","minarea":360,"maxarea":430},{"newCode":"1210971608","title":"虹桥正荣府","purpose":"住宅","x":121.282074,"y":31.156564,"price_num":"53000","price_unit":"元/平","minarea":189,"maxarea":189},{"newCode":"1210956364","title":"金茂逸墅","purpose":"别墅","x":121.806481,"y":31.465693,"price_num":"3200","price_unit":"万元/套","minarea":925,"maxarea":925},{"newCode":"1210955120","title":"中建大公馆","purpose":"别墅","x":121.515129,"y":31.33075,"price_num":"150000","price_unit":"元/平","minarea":412,"maxarea":412},{"newCode":"1210954850","title":"国信世纪海景","purpose":"住宅","x":121.513774,"y":31.212304,"price_num":"20000","price_unit":"万元/套","minarea":0,"maxarea":0},{"newCode":"1210930636","title":"乔爱庄园","purpose":"别墅","x":121.344666,"y":31.082075,"price_num":"2000","price_unit":"万元/套","minarea":558,"maxarea":676},{"newCode":"1210929492","title":"晶苑四季御庭四期","purpose":"别墅","x":121.333798,"y":31.076435,"price_num":"1300","price_unit":"万元/套","minarea":323,"maxarea":371},{"newCode":"1210921636","title":"金地天境","purpose":"住宅","x":121.224431,"y":31.124371,"price_num":"46000","price_unit":"元/平","minarea":140,"maxarea":160},{"newCode":"1210921528","title":"古北香堤艺墅","purpose":"别墅","x":121.043337,"y":31.109253,"price_num":"900","price_unit":"万元/套","minarea":250,"maxarea":262},{"newCode":"1210921456","title":"佘山玺樾","purpose":"别墅","x":121.192435,"y":31.066322,"price_num":"50000","price_unit":"元/平","minarea":223,"maxarea":267},{"newCode":"1210917622","title":"华润中央公园湖墅","purpose":"住宅","x":121.313303,"y":31.3138,"price_num":"50000","price_unit":"元/平","minarea":84,"maxarea":147},{"newCode":"1210909000","title":"中环国际公寓三期","purpose":"住宅","x":121.428064,"y":31.333257,"price_num":"50000","price_unit":"元/平","minarea":58,"maxarea":157},{"newCode":"1210908130","title":"融科托斯卡纳庄园","purpose":"别墅","x":121.418422,"y":31.798077,"price_num":"16000","price_unit":"元/平","minarea":186,"maxarea":212},{"newCode":"1210906376","title":"东郊壹号","purpose":"别墅","x":121.599942,"y":31.22107,"price_num":"18500","price_unit":"万元/套","minarea":587,"maxarea":670},{"newCode":"1210895760","title":"绿洲香格丽花园别墅","purpose":"别墅","x":121.280742,"y":31.420144,"price_num":"800","price_unit":"万元/套","minarea":188,"maxarea":310},{"newCode":"1210892086","title":"上海星河湾","purpose":"住宅","x":121.408524,"y":31.088252,"price_num":"76500","price_unit":"元/平","minarea":220,"maxarea":220},{"newCode":"1210877030","title":"香水湾别墅","purpose":"别墅","x":121.241923,"y":31.152966,"price_num":"60000","price_unit":"元/平","minarea":300,"maxarea":300},{"newCode":"1210864642","title":"景源名墅","purpose":"别墅","x":121.419262,"y":30.907409,"price_num":"900","price_unit":"万元/套","minarea":333,"maxarea":404},{"newCode":"1210859340","title":"金球怡云花园玫瑰里","purpose":"别墅","x":121.285946,"y":31.206783,"price_num":"65000","price_unit":"元/平","minarea":230,"maxarea":247},{"newCode":"1210858766","title":"御涛园","purpose":"别墅","x":121.352029,"y":31.044789,"price_num":"3000","price_unit":"万元/套","minarea":0,"maxarea":0},{"newCode":"1210856192","title":"正阳世纪星城别墅","purpose":"别墅","x":121.479249,"y":30.906754,"price_num":"3000","price_unit":"万元/套","minarea":361,"maxarea":372},{"newCode":"1210843538","title":"远香湖九号","purpose":"别墅","x":121.264759,"y":31.346126,"price_num":"40000","price_unit":"元/平","minarea":206,"maxarea":247},{"newCode":"1210843138","title":"祥生御江湾别墅","purpose":"别墅","x":121.497447,"y":31.332087,"price_num":"2500","price_unit":"万元/套","minarea":300,"maxarea":300},{"newCode":"1210841738","title":"贝尚湾溪谷墅","purpose":"别墅","x":121.319054,"y":31.145993,"price_num":"2000","price_unit":"万元/套","minarea":0,"maxarea":0},{"newCode":"1210840146","title":"汇贤阁别墅","purpose":"别墅","x":121.308619,"y":31.149927,"price_num":"5800","price_unit":"万元/套","minarea":0,"maxarea":0},{"newCode":"1210838994","title":"天和湖滨艺墅","purpose":"别墅","x":121.754159,"y":31.179772,"price_num":"800","price_unit":"万元/套","minarea":200,"maxarea":282},{"newCode":"1210838916","title":"金领国际别墅","purpose":"别墅","x":121.68021,"y":31.254204,"price_num":"62000","price_unit":"元/平","minarea":271,"maxarea":271},{"newCode":"1210836220","title":"虹桥1号","purpose":"住宅","x":121.332346,"y":31.223817,"price_num":"待定","price_unit":"","minarea":86,"maxarea":117},{"newCode":"1210801940","title":"御品园林","purpose":"别墅","x":121.266119,"y":31.151656,"price_num":"2000","price_unit":"万元/套","minarea":473,"maxarea":500},{"newCode":"1210795630","title":"览海国际高尔夫社区","purpose":"别墅","x":121.82097,"y":31.462877,"price_num":"1500","price_unit":"万元/套","minarea":0,"maxarea":0},{"newCode":"1210785460","title":"保亿风景水岸","purpose":"别墅","x":121.808195,"y":31.465803,"price_num":"850","price_unit":"万元/套","minarea":300,"maxarea":340},{"newCode":"1210778584","title":"涵璧湾","purpose":"别墅","x":120.975409,"y":31.054727,"price_num":"待定","price_unit":"","minarea":757,"maxarea":1027},{"newCode":"1210770900","title":"时代御湖","purpose":"别墅","x":120.966606,"y":31.188607,"price_num":"800","price_unit":"万元/套","minarea":550,"maxarea":550},{"newCode":"1210749320","title":"湖庭","purpose":"别墅","x":121.023493,"y":31.127148,"price_num":"3600","price_unit":"万元/套","minarea":598,"maxarea":603},{"newCode":"1210704428","title":"万顺水原墅","purpose":"别墅","x":121.416216,"y":31.042747,"price_num":"60000","price_unit":"元/平","minarea":284,"maxarea":345},{"newCode":"1210642928","title":"江畔御庭","purpose":"别墅","x":121.773311,"y":31.205296,"price_num":"1500","price_unit":"万元/套","minarea":346,"maxarea":500},{"newCode":"1210613360","title":"君庭","purpose":"别墅","x":121.604903,"y":31.223926,"price_num":"28000","price_unit":"万元/套","minarea":800,"maxarea":1350},{"newCode":"1210517702","title":"绿城黄浦湾","purpose":"住宅","x":121.503662,"y":31.218287,"price_num":"7000","price_unit":"万元/套","minarea":331,"maxarea":460},{"newCode":"1210509622","title":"棕榈滩高尔夫别墅","purpose":"别墅","x":121.554284,"y":30.827513,"price_num":"35000","price_unit":"元/平","minarea":332,"maxarea":421},{"newCode":"1210505302","title":"绿波景园","purpose":"住宅","x":121.271196,"y":31.10802,"price_num":"36000","price_unit":"元/平","minarea":90,"maxarea":136},{"newCode":"1210477742","title":"品尊国际","purpose":"住宅","x":121.420601,"y":31.256758,"price_num":"100000","price_unit":"元/平","minarea":156,"maxarea":260},{"newCode":"1210472542","title":"佘山东紫园","purpose":"别墅","x":121.213546,"y":31.09003,"price_num":"3500","price_unit":"万元/套","minarea":630,"maxarea":630},{"newCode":"1210360942","title":"花源湾","purpose":"别墅","x":121.709874,"y":31.046097,"price_num":"900","price_unit":"万元/套","minarea":195,"maxarea":260},{"newCode":"1210325154","title":"佘山东郡","purpose":"别墅","x":121.239978,"y":31.102952,"price_num":"48000","price_unit":"元/平","minarea":324,"maxarea":457},{"newCode":"1210307822","title":"圣得庄园","purpose":"别墅","x":121.408149,"y":31.062125,"price_num":"待定","price_unit":"","minarea":300,"maxarea":670},{"newCode":"1210159022","title":"旭辉铂悦西郊","purpose":"别墅","x":121.191366,"y":31.265271,"price_num":"1700","price_unit":"万元/套","minarea":255,"maxarea":255},{"newCode":"1210148062","title":"融创香溢花城","purpose":"住宅","x":121.433427,"y":31.256085,"price_num":"98000","price_unit":"元/平","minarea":185,"maxarea":195},{"newCode":"1210144382","title":"华山夏都苑","purpose":"住宅","x":121.430655,"y":31.207486,"price_num":"130000","price_unit":"元/平","minarea":348,"maxarea":348},{"newCode":"1210125302","title":"世纪长江苑","purpose":"住宅","x":121.393463,"y":31.352307,"price_num":"36000","price_unit":"元/平","minarea":100,"maxarea":100},{"newCode":"1210094921","title":"帕缇欧香苑","purpose":"别墅","x":121.124013,"y":31.139147,"price_num":"36000","price_unit":"元/平","minarea":118,"maxarea":162},{"newCode":"1210078420","title":"中凯曼荼园","purpose":"别墅","x":121.173772,"y":31.078483,"price_num":"128000","price_unit":"元/平","minarea":580,"maxarea":580},{"newCode":"1210071642","title":"汤臣一品","purpose":"住宅","x":121.501214,"y":31.233418,"price_num":"200000","price_unit":"元/平","minarea":434,"maxarea":597},{"newCode":"1210071068","title":"湖山在望花园","purpose":"别墅","x":121.408611,"y":31.068516,"price_num":"待定","price_unit":"","minarea":350,"maxarea":548},{"newCode":"1210070401","title":"大宁揽翠艺墅","purpose":"别墅","x":121.457155,"y":31.288742,"price_num":"120000","price_unit":"元/平","minarea":260,"maxarea":260},{"newCode":"1210070025","title":"中粮海景壹号","purpose":"住宅","x":121.50352,"y":31.231505,"price_num":"250000","price_unit":"元/平","minarea":592,"maxarea":592},{"newCode":"1210067999","title":"大豪山林别墅","purpose":"别墅","x":121.251308,"y":31.169029,"price_num":"2500","price_unit":"万元/套","minarea":366,"maxarea":761},{"newCode":"1210066781","title":"海湾艺墅","purpose":"别墅","x":121.524517,"y":30.823242,"price_num":"900","price_unit":"万元/套","minarea":0,"maxarea":0},{"newCode":"1210037693","title":"月湖山庄","purpose":"别墅","x":121.221573,"y":31.100067,"price_num":"3000","price_unit":"万元/套","minarea":580,"maxarea":855},{"newCode":"1210032159","title":"紫都上海晶园","purpose":"别墅","x":121.192305,"y":31.103482,"price_num":"2500","price_unit":"万元/套","minarea":320,"maxarea":380},{"newCode":"1210126146","title":"上海星光耀广场","purpose":"写字楼","x":121.407148,"y":31.257167,"price_num":"45000","price_unit":"元/平","minarea":0,"maxarea":0},{"newCode":"1210125178","title":"中信泰富又一城四期","purpose":"写字楼","x":121.255293,"y":31.330597,"price_num":"待定","price_unit":"","minarea":0,"maxarea":0},{"newCode":"1211267730","title":"七莘红点城","purpose":"写字楼","x":121.362865,"y":31.133929,"price_num":"待定","price_unit":"","minarea":0,"maxarea":0},{"newCode":"1210126238","title":"万科翡翠公园商铺","purpose":"商铺","x":121.610248,"y":31.179665,"price_num":"811","price_unit":"万元/套","minarea":0,"maxarea":0},{"newCode":"1210126414","title":"保利玲珑公馆","purpose":"住宅","x":121.854963,"y":30.866953,"price_num":"待定","price_unit":"","minarea":0,"maxarea":0},{"newCode":"1210126254","title":"新城西岸公园","purpose":"住宅","x":121.576311,"y":31.125321,"price_num":"待定","price_unit":"","minarea":0,"maxarea":0},{"newCode":"1210126044","title":"中山学林苑","purpose":"住宅","x":121.423684,"y":31.216091,"price_num":"待定","price_unit":"","minarea":160,"maxarea":200},{"newCode":"1210125998","title":"绿地海湾","purpose":"住宅","x":121.230363,"y":30.348831,"price_num":"待定","price_unit":"","minarea":84,"maxarea":106},{"newCode":"1210125992","title":"紫藤华庭","purpose":"住宅","x":121.364198,"y":31.169974,"price_num":"待定","price_unit":"","minarea":0,"maxarea":0},{"newCode":"1210125856","title":"卓越维港","purpose":"住宅","x":121.376008,"y":31.021157,"price_num":"待定","price_unit":"","minarea":87,"maxarea":87},{"newCode":"1210125570","title":"新华御湖上园","purpose":"住宅","x":121.313488,"y":30.83064,"price_num":"待定","price_unit":"","minarea":82,"maxarea":89},{"newCode":"1210125480","title":"TODTOWN天荟悦麓","purpose":"住宅","x":121.385053,"y":31.111525,"price_num":"待定","price_unit":"","minarea":103,"maxarea":177},{"newCode":"1210125190","title":"金辉海上铭著","purpose":"住宅","x":121.394482,"y":31.113228,"price_num":"待定","price_unit":"","minarea":0,"maxarea":0},{"newCode":"1210124906","title":"东方城市豪庭","purpose":"住宅","x":121.766175,"y":31.048385,"price_num":"待定","price_unit":"","minarea":75,"maxarea":140},{"newCode":"1211282382","title":"沁和园","purpose":"住宅","x":121.382952,"y":31.227436,"price_num":"待定","price_unit":"","minarea":0,"maxarea":0},{"newCode":"1211271270","title":"华府天地愉园","purpose":"别墅","x":121.357413,"y":31.051693,"price_num":"待定","price_unit":"","minarea":149,"maxarea":191},{"newCode":"1211254140","title":"绿地海珀玉晖","purpose":"住宅","x":121.420317,"y":31.226668,"price_num":"待定","price_unit":"","minarea":143,"maxarea":285},{"newCode":"1211202152","title":"宝华源墅","purpose":"别墅","x":121.509147,"y":31.119379,"price_num":"待定","price_unit":"","minarea":178,"maxarea":241},{"newCode":"1211078202","title":"云锦东方","purpose":"住宅","x":121.457367,"y":31.166002,"price_num":"待定","price_unit":"","minarea":0,"maxarea":0},{"newCode":"1211076678","title":"御沁园公寓","purpose":"住宅","x":121.57563,"y":31.102837,"price_num":"待定","price_unit":"","minarea":0,"maxarea":0},{"newCode":"1211037094","title":"御沁园","purpose":"别墅","x":121.574406,"y":31.103721,"price_num":"待定","price_unit":"","minarea":0,"maxarea":0},{"newCode":"1210893958","title":"鼎荣地产嘉定老城区项目","purpose":"住宅","x":121.330729,"y":31.320034,"price_num":"待定","price_unit":"","minarea":0,"maxarea":0},{"newCode":"1210730818","title":"滨江凯旋门","purpose":"住宅","x":121.510668,"y":31.22364,"price_num":"待定","price_unit":"","minarea":280,"maxarea":280},{"newCode":"1210040155","title":"象源丽都","purpose":"住宅","x":121.376743,"y":31.235446,"price_num":"待定","price_unit":"","minarea":0,"maxarea":0},{"newCode":"1210126274","title":"宝邸院墅","purpose":"别墅","x":121.333057,"y":31.48038,"price_num":"1100","price_unit":"万元/套","minarea":310,"maxarea":310},{"newCode":"1210126192","title":"嘉善东鼎名人府邸二期","purpose":"住宅","x":120.883252,"y":30.896102,"price_num":"14000","price_unit":"元/平","minarea":41,"maxarea":100},{"newCode":"1211289620","title":"丽江复华度假世界","purpose":"商铺","x":100.221715,"y":26.923971,"price_num":"16000","price_unit":"元/平","minarea":40,"maxarea":58},{"newCode":"1211289274","title":"昆山万科海上传奇","purpose":"住宅","x":120.961535,"y":31.181061,"price_num":"19000","price_unit":"元/平","minarea":90,"maxarea":90},{"newCode":"1211288986","title":"新城海上风华","purpose":"住宅","x":120.921501,"y":30.819956,"price_num":"17800","price_unit":"元/平","minarea":70,"maxarea":95},{"newCode":"1210125306","title":"佳兆业君汇上品","purpose":"住宅","x":121.194659,"y":31.195951,"price_num":"31000","price_unit":"元/平","minarea":79,"maxarea":119},{"newCode":"1210125300","title":"新城盛世","purpose":"住宅","x":121.101186,"y":31.161179,"price_num":"42000","price_unit":"元/平","minarea":95,"maxarea":134},{"newCode":"1210124584","title":"天健萃园","purpose":"住宅","x":121.807592,"y":30.955458,"price_num":"23000","price_unit":"元/平","minarea":75,"maxarea":102},{"newCode":"1211283922","title":"崇明三湘森林海尚","purpose":"别墅","x":121.833797,"y":31.458239,"price_num":"31000","price_unit":"元/平","minarea":172,"maxarea":295},{"newCode":"1211280328","title":"临港首府","purpose":"住宅","x":121.905898,"y":30.899863,"price_num":"27000","price_unit":"元/平","minarea":108,"maxarea":311},{"newCode":"1211224984","title":"远洋万和四季","purpose":"住宅","x":121.785827,"y":31.061967,"price_num":"31700","price_unit":"元/平","minarea":80,"maxarea":120},{"newCode":"1211198900","title":"万科公园大道","purpose":"住宅","x":121.380481,"y":31.025117,"price_num":"455","price_unit":"万元/套","minarea":67,"maxarea":126},{"newCode":"1211174764","title":"保利艾庐","purpose":"住宅","x":121.642282,"y":31.097528,"price_num":"43423","price_unit":"元/平","minarea":151,"maxarea":151},{"newCode":"1211125790","title":"尚汇豪庭","purpose":"住宅","x":121.430771,"y":31.1793,"price_num":"待定","price_unit":"","minarea":0,"maxarea":0},{"newCode":"1211111360","title":"悦上海","purpose":"住宅","x":121.034473,"y":31.178308,"price_num":"17000","price_unit":"元/平","minarea":93,"maxarea":93},{"newCode":"1211081716","title":"万科mixtown","purpose":"住宅","x":121.076271,"y":31.276906,"price_num":"18000","price_unit":"元/平","minarea":68,"maxarea":135},{"newCode":"1211074366","title":"水月周庄","purpose":"别墅","x":120.860999,"y":31.125742,"price_num":"13000","price_unit":"元/平","minarea":117,"maxarea":434},{"newCode":"1210893964","title":"碧云壹零","purpose":"住宅","x":121.899569,"y":30.903129,"price_num":"27000","price_unit":"元/平","minarea":182,"maxarea":253},{"newCode":"1210878392","title":"新虹桥首府别墅","purpose":"别墅","x":121.304464,"y":31.150574,"price_num":"待定","price_unit":"","minarea":0,"maxarea":0},{"newCode":"1210867814","title":"西康路989","purpose":"住宅","x":121.441399,"y":31.24066,"price_num":"待定","price_unit":"","minarea":0,"maxarea":0},{"newCode":"1210792342","title":"万业紫辰苑","purpose":"住宅","x":121.438984,"y":31.399616,"price_num":"40800","price_unit":"元/平","minarea":86,"maxarea":142},{"newCode":"1210613308","title":"凤凰城","purpose":"住宅","x":121.416711,"y":31.019738,"price_num":"50000","price_unit":"元/平","minarea":104,"maxarea":139},{"newCode":"1210100209","title":"中鹰黑森林","purpose":"住宅","x":121.410289,"y":31.269856,"price_num":"120000","price_unit":"元/平","minarea":202,"maxarea":235},{"newCode":"1210125878","title":"融创香溢花城三期商铺","purpose":"商铺","x":121.433427,"y":31.256075,"price_num":"100000","price_unit":"元/平","minarea":0,"maxarea":0},{"newCode":"1210126312","title":"艾森公馆","purpose":"住宅","x":121.926256,"y":30.905373,"price_num":"待定","price_unit":"","minarea":0,"maxarea":0},{"newCode":"1210125824","title":"颐盛御中环","purpose":"住宅","x":121.559385,"y":31.1518,"price_num":"待定","price_unit":"","minarea":95,"maxarea":115},{"newCode":"1210125738","title":"大发融悦四季","purpose":"住宅","x":121.150284,"y":31.153201,"price_num":"待定","price_unit":"","minarea":85,"maxarea":95},{"newCode":"1210125720","title":"嘉和美苑","purpose":"住宅","x":121.925592,"y":30.903953,"price_num":"待定","price_unit":"","minarea":105,"maxarea":251},{"newCode":"1210125034","title":"瑞和上海印象","purpose":"住宅","x":121.742969,"y":30.895518,"price_num":"待定","price_unit":"","minarea":74,"maxarea":101},{"newCode":"1210125006","title":"保利熙悦","purpose":"住宅","x":121.37387,"y":31.307716,"price_num":"待定","price_unit":"","minarea":98,"maxarea":117},{"newCode":"1210124576","title":"瑞虹新城悦庭","purpose":"住宅","x":121.499087,"y":31.265366,"price_num":"待定","price_unit":"","minarea":147,"maxarea":190},{"newCode":"1211267910","title":"同润金色橘苑","purpose":"住宅","x":121.808587,"y":30.958133,"price_num":"待定","price_unit":"","minarea":78,"maxarea":92},{"newCode":"1211194826","title":"恒大帝景（备案名：恒大茸景佳苑）","purpose":"住宅","x":121.251474,"y":31.040414,"price_num":"待定","price_unit":"","minarea":0,"maxarea":0},{"newCode":"1210124912","title":"碧桂园世纪城","purpose":"住宅","x":121.011657,"y":31.243601,"price_num":"14500","price_unit":"元/平","minarea":0,"maxarea":0},{"newCode":"1211268388","title":"新西塘孔雀城","purpose":"住宅","x":120.924066,"y":30.7957,"price_num":"14000","price_unit":"元/平","minarea":77,"maxarea":130},{"newCode":"1211140800","title":"国贸天悦（备案名：佘北家园观澜庭）","purpose":"住宅","x":121.219527,"y":31.127092,"price_num":"41000","price_unit":"元/平","minarea":53,"maxarea":132},{"newCode":"1211081680","title":"大华朗香花园","purpose":"住宅","x":121.380155,"y":31.320701,"price_num":"53000","price_unit":"元/平","minarea":96,"maxarea":130},{"newCode":"1210799104","title":"智富中环尚城","purpose":"住宅","x":121.393456,"y":31.28288,"price_num":"86000","price_unit":"元/平","minarea":91,"maxarea":118},{"newCode":"1210125882","title":"莘庄中心","purpose":"写字楼","x":121.365267,"y":31.124051,"price_num":"待定","price_unit":"","minarea":0,"maxarea":0},{"newCode":"1211108904","title":"长风中心诚公馆","purpose":"写字楼","x":121.389998,"y":31.227567,"price_num":"待定","price_unit":"","minarea":0,"maxarea":0},{"newCode":"1210125416","title":"梧桐国际","purpose":"写字楼","x":121.628803,"y":31.109469,"price_num":"待定","price_unit":"","minarea":0,"maxarea":0},{"newCode":"1211055746","title":"旭辉浦江国际","purpose":"写字楼","x":121.514699,"y":31.077882,"price_num":"30000","price_unit":"元/平","minarea":0,"maxarea":0},{"newCode":"1210125980","title":"后TOWN","purpose":"商铺","x":121.474776,"y":31.242948,"price_num":"待定","price_unit":"","minarea":0,"maxarea":0},{"newCode":"1210126314","title":"华园","purpose":"住宅","x":121.392572,"y":31.193402,"price_num":"待定","price_unit":"","minarea":49,"maxarea":127},{"newCode":"1210126292","title":"象屿虹桥悦府","purpose":"住宅","x":121.328998,"y":31.13654,"price_num":"待定","price_unit":"","minarea":77,"maxarea":120},{"newCode":"1210126154","title":"雍和府","purpose":"住宅","x":121.338917,"y":31.478984,"price_num":"待定","price_unit":"","minarea":89,"maxarea":120},{"newCode":"1210126132","title":"云麓之城","purpose":"住宅","x":121.340305,"y":31.428254,"price_num":"待定","price_unit":"","minarea":75,"maxarea":124},{"newCode":"1210125966","title":"凤凰城天境","purpose":"住宅","x":121.747248,"y":30.876908,"price_num":"待定","price_unit":"","minarea":0,"maxarea":0},{"newCode":"1210125906","title":"新里波洛克公馆","purpose":"住宅","x":121.194838,"y":31.199796,"price_num":"待定","price_unit":"","minarea":82,"maxarea":120},{"newCode":"1210125892","title":"东方颐城","purpose":"住宅","x":121.884979,"y":30.975751,"price_num":"23000","price_unit":"元/平","minarea":83,"maxarea":123},{"newCode":"1210125836","title":"宝华帝华园","purpose":"住宅","x":121.573074,"y":30.924125,"price_num":"待定","price_unit":"","minarea":59,"maxarea":124},{"newCode":"1210125812","title":"上海桃花源","purpose":"别墅","x":121.493354,"y":31.106699,"price_num":"待定","price_unit":"","minarea":0,"maxarea":0},{"newCode":"1210125762","title":"华谊逸品澜湾","purpose":"住宅","x":121.302612,"y":31.306904,"price_num":"待定","price_unit":"","minarea":78,"maxarea":111},{"newCode":"1210125718","title":"运杰御澜雅苑","purpose":"住宅","x":121.146852,"y":31.153478,"price_num":"待定","price_unit":"","minarea":96,"maxarea":125},{"newCode":"1210125700","title":"金地双都汇","purpose":"住宅","x":121.344816,"y":31.076147,"price_num":"待定","price_unit":"","minarea":116,"maxarea":125},{"newCode":"1210125340","title":"桐南美麓","purpose":"住宅","x":121.484947,"y":30.956062,"price_num":"待定","price_unit":"","minarea":79,"maxarea":149},{"newCode":"1211191032","title":"天和前滩时代","purpose":"住宅","x":121.51693,"y":30.970396,"price_num":"待定","price_unit":"","minarea":64,"maxarea":85},{"newCode":"1211152528","title":"朗诗未来街区","purpose":"住宅","x":121.508527,"y":30.970845,"price_num":"待定","price_unit":"","minarea":76,"maxarea":86},{"newCode":"1210921826","title":"中冶枫郡别墅","purpose":"别墅","x":121.018394,"y":30.908607,"price_num":"待定","price_unit":"","minarea":0,"maxarea":0},{"newCode":"1210126122","title":"绿地天呈别墅","purpose":"别墅","x":121.240414,"y":31.396929,"price_num":"550","price_unit":"万元/套","minarea":133,"maxarea":152},{"newCode":"1210126116","title":"新南浔孔雀城","purpose":"住宅","x":120.418576,"y":30.84192,"price_num":"8000","price_unit":"元/平","minarea":89,"maxarea":140},{"newCode":"1210125996","title":"国瑞瀛台","purpose":"住宅","x":121.488866,"y":31.759989,"price_num":"11500","price_unit":"元/平","minarea":67,"maxarea":158},{"newCode":"1210125838","title":"中国铁建香榭国际","purpose":"住宅","x":121.436603,"y":30.988685,"price_num":"37800","price_unit":"元/平","minarea":89,"maxarea":123},{"newCode":"1211289054","title":"碧桂园十里江南","purpose":"别墅","x":120.86764,"y":31.088794,"price_num":"18200","price_unit":"元/平","minarea":110,"maxarea":172},{"newCode":"1210125712","title":"新城上坤樾山明月","purpose":"别墅","x":121.233951,"y":31.097367,"price_num":"1250","price_unit":"万元/套","minarea":127,"maxarea":128},{"newCode":"1210125702","title":"碧桂园十里外滩","purpose":"住宅","x":121.584519,"y":31.728331,"price_num":"11500","price_unit":"元/平","minarea":95,"maxarea":140},{"newCode":"1210125224","title":"宝华城市之星","purpose":"住宅","x":121.43052,"y":31.254699,"price_num":"98000","price_unit":"元/平","minarea":100,"maxarea":107},{"newCode":"1210124570","title":"招商中环华府","purpose":"住宅","x":121.393564,"y":31.307059,"price_num":"51300","price_unit":"元/平","minarea":100,"maxarea":125},{"newCode":"1211270602","title":"上海长滩","purpose":"住宅","x":121.475812,"y":31.415277,"price_num":"55000","price_unit":"元/平","minarea":86,"maxarea":244},{"newCode":"1211267442","title":"绿地黄浦滨江","purpose":"住宅","x":121.481905,"y":31.196487,"price_num":"7000","price_unit":"万元/套","minarea":0,"maxarea":0},{"newCode":"1211102042","title":"中金海棠湾别墅","purpose":"别墅","x":121.591908,"y":31.099055,"price_num":"55000","price_unit":"元/平","minarea":234,"maxarea":268},{"newCode":"1210597386","title":"合生东郊别墅","purpose":"别墅","x":121.600207,"y":31.223906,"price_num":"9500","price_unit":"万元/套","minarea":431,"maxarea":654},{"newCode":"1211078344","title":"中金海棠湾","purpose":"住宅","x":121.59086,"y":31.100069,"price_num":"48000","price_unit":"元/平","minarea":130,"maxarea":145},{"newCode":"1211173646","title":"信义嘉庭","purpose":"住宅","x":121.273901,"y":31.372259,"price_num":"500","price_unit":"万元/套","minarea":90,"maxarea":150},{"newCode":"1211189358","title":"绿地长岛","purpose":"住宅","x":121.465059,"y":31.79909,"price_num":"11000","price_unit":"元/平","minarea":49,"maxarea":142},{"newCode":"1210125312","title":"金地世家","purpose":"住宅","x":121.259711,"y":31.326709,"price_num":"42000","price_unit":"元/平","minarea":139,"maxarea":139},{"newCode":"1210126102","title":"新城上坤樾山半岛","purpose":"别墅","x":121.247659,"y":31.097145,"price_num":"待定","price_unit":"","minarea":114,"maxarea":139},{"newCode":"1210125274","title":"信达蓝尊","purpose":"住宅","x":121.254467,"y":31.058874,"price_num":"45600","price_unit":"元/平","minarea":77,"maxarea":114}]